frieren/__init__.py
frieren/base/__init__.py
frieren/base/dtypes.py
frieren/base/locator.py
frieren/base/metadata.py
frieren/base/operator.py
frieren/base/repository.py
frieren-0.1.1.dist-info/LICENSE
frieren-0.1.1.dist-info/METADATA
frieren-0.1.1.dist-info/WHEEL
frieren-0.1.1.dist-info/top_level.txt
frieren-0.1.1.dist-info/RECORD
