Metadata-Version: 2.1
Name: frieren
Version: 0.1.1
Summary: A package for file management operations with abstract base classes.
Author: nodashin
Project-URL: Homepage, https://github.com/nodashin6/frieren
Classifier: Development Status :: 3 - Alpha
Classifier: Intended Audience :: Developers
Classifier: License :: OSI Approved :: MIT License
Classifier: Programming Language :: Python :: 3
Classifier: Programming Language :: Python :: 3.8
Classifier: Programming Language :: Python :: 3.9
Classifier: Programming Language :: Python :: 3.10
Requires-Python: >=3.8
License-File: LICENSE
Requires-Dist: pytest>=8.1.1
